{
   "library" : {
      "annotation" : [ {
         "translatorVersion" : "3.27.0",
         "translatorOptions" : "EnableLocators,EnableResultTypes",
         "signatureLevel" : "All",
         "type" : "CqlToElmInfo"
      } ],
      "identifier" : {
         "id" : "TJCOverall",
         "version" : "8.15.000"
      },
      "schemaIdentifier" : {
         "id" : "urn:hl7-org:elm",
         "version" : "r1"
      },
      "usings" : {
         "def" : [ {
            "localIdentifier" : "System",
            "uri" : "urn:hl7-org:elm-types:r1",
            "annotation" : [ ]
         }, {
            "locator" : "4:1-4:28",
            "localIdentifier" : "QICore",
            "uri" : "http://hl7.org/fhir",
            "annotation" : [ ]
         } ]
      },
      "includes" : {
         "def" : [ {
            "locator" : "6:1-6:56",
            "localIdentifier" : "FHIRHelpers",
            "path" : "FHIRHelpers",
            "version" : "4.4.000",
            "annotation" : [ ]
         }, {
            "locator" : "7:1-7:54",
            "localIdentifier" : "CQMCommon",
            "path" : "CQMCommon",
            "version" : "2.2.000",
            "annotation" : [ ]
         }, {
            "locator" : "8:1-8:58",
            "localIdentifier" : "QICoreCommon",
            "path" : "QICoreCommon",
            "version" : "2.1.000",
            "annotation" : [ ]
         } ]
      },
      "parameters" : {
         "def" : [ {
            "locator" : "19:1-20:72",
            "name" : "Measurement Period",
            "accessLevel" : "Public",
            "annotation" : [ ],
            "resultTypeSpecifier" : {
               "type" : "IntervalTypeSpecifier",
               "annotation" : [ ],
               "pointType" : {
                  "name" : "{urn:hl7-org:elm-types:r1}DateTime",
                  "type" : "NamedTypeSpecifier",
                  "annotation" : [ ]
               }
            },
            "default" : {
               "locator" : "20:11-20:72",
               "lowClosed" : true,
               "highClosed" : true,
               "type" : "Interval",
               "annotation" : [ ],
               "resultTypeSpecifier" : {
                  "type" : "IntervalTypeSpecifier",
                  "annotation" : [ ],
                  "pointType" : {
                     "name" : "{urn:hl7-org:elm-types:r1}DateTime",
                     "type" : "NamedTypeSpecifier",
                     "annotation" : [ ]
                  }
               },
               "low" : {
                  "locator" : "20:20-20:44",
                  "resultTypeName" : "{urn:hl7-org:elm-types:r1}DateTime",
                  "type" : "DateTime",
                  "annotation" : [ ],
                  "signature" : [ ],
                  "year" : {
                     "valueType" : "{urn:hl7-org:elm-types:r1}Integer",
                     "value" : "2026",
                     "type" : "Literal",
                     "annotation" : [ ]
                  },
                  "month" : {
                     "valueType" : "{urn:hl7-org:elm-types:r1}Integer",
                     "value" : "1",
                     "type" : "Literal",
                     "annotation" : [ ]
                  },
                  "day" : {
                     "valueType" : "{urn:hl7-org:elm-types:r1}Integer",
                     "value" : "1",
                     "type" : "Literal",
                     "annotation" : [ ]
                  },
                  "hour" : {
                     "valueType" : "{urn:hl7-org:elm-types:r1}Integer",
                     "value" : "0",
                     "type" : "Literal",
                     "annotation" : [ ]
                  },
                  "minute" : {
                     "valueType" : "{urn:hl7-org:elm-types:r1}Integer",
                     "value" : "0",
                     "type" : "Literal",
                     "annotation" : [ ]
                  },
                  "second" : {
                     "valueType" : "{urn:hl7-org:elm-types:r1}Integer",
                     "value" : "0",
                     "type" : "Literal",
                     "annotation" : [ ]
                  },
                  "millisecond" : {
                     "valueType" : "{urn:hl7-org:elm-types:r1}Integer",
                     "value" : "0",
                     "type" : "Literal",
                     "annotation" : [ ]
                  },
                  "timezoneOffset" : {
                     "valueType" : "{urn:hl7-org:elm-types:r1}Decimal",
                     "value" : "0.0",
                     "type" : "Literal",
                     "annotation" : [ ]
                  }
               },
               "high" : {
                  "locator" : "20:47-20:71",
                  "resultTypeName" : "{urn:hl7-org:elm-types:r1}DateTime",
                  "type" : "DateTime",
                  "annotation" : [ ],
                  "signature" : [ ],
                  "year" : {
                     "valueType" : "{urn:hl7-org:elm-types:r1}Integer",
                     "value" : "2026",
                     "type" : "Literal",
                     "annotation" : [ ]
                  },
                  "month" : {
                     "valueType" : "{urn:hl7-org:elm-types:r1}Integer",
                     "value" : "12",
                     "type" : "Literal",
                     "annotation" : [ ]
                  },
                  "day" : {
                     "valueType" : "{urn:hl7-org:elm-types:r1}Integer",
                     "value" : "31",
                     "type" : "Literal",
                     "annotation" : [ ]
                  },
                  "hour" : {
                     "valueType" : "{urn:hl7-org:elm-types:r1}Integer",
                     "value" : "23",
                     "type" : "Literal",
                     "annotation" : [ ]
                  },
                  "minute" : {
                     "valueType" : "{urn:hl7-org:elm-types:r1}Integer",
                     "value" : "59",
                     "type" : "Literal",
                     "annotation" : [ ]
                  },
                  "second" : {
                     "valueType" : "{urn:hl7-org:elm-types:r1}Integer",
                     "value" : "59",
                     "type" : "Literal",
                     "annotation" : [ ]
                  },
                  "millisecond" : {
                     "valueType" : "{urn:hl7-org:elm-types:r1}Integer",
                     "value" : "999",
                     "type" : "Literal",
                     "annotation" : [ ]
                  },
                  "timezoneOffset" : {
                     "valueType" : "{urn:hl7-org:elm-types:r1}Decimal",
                     "value" : "0.0",
                     "type" : "Literal",
                     "annotation" : [ ]
                  }
               }
            },
            "parameterTypeSpecifier" : {
               "locator" : "19:32-19:49",
               "type" : "IntervalTypeSpecifier",
               "annotation" : [ ],
               "resultTypeSpecifier" : {
                  "localId" : "254",
                  "type" : "IntervalTypeSpecifier",
                  "pointType" : {
                     "localId" : "255",
                     "name" : "{urn:hl7-org:elm-types:r1}DateTime",
                     "type" : "NamedTypeSpecifier"
                  }
               },
               "pointType" : {
                  "locator" : "19:41-19:48",
                  "resultTypeName" : "{urn:hl7-org:elm-types:r1}DateTime",
                  "name" : "{urn:hl7-org:elm-types:r1}DateTime",
                  "type" : "NamedTypeSpecifier",
                  "annotation" : [ ]
               }
            }
         } ]
      },
      "valueSets" : {
         "def" : [ {
            "locator" : "10:1-10:94",
            "resultTypeName" : "{urn:hl7-org:elm-types:r1}ValueSet",
            "name" : "Comfort Measures",
            "id" : "http://cts.nlm.nih.gov/fhir/ValueSet/1.3.6.1.4.1.33895.1.3.0.45",
            "accessLevel" : "Public",
            "annotation" : [ ],
            "codeSystem" : [ ]
         }, {
            "locator" : "11:1-11:116",
            "resultTypeName" : "{urn:hl7-org:elm-types:r1}ValueSet",
            "name" : "Discharge To Acute Care Facility",
            "id" : "http://cts.nlm.nih.gov/fhir/ValueSet/2.16.840.1.113883.3.117.1.7.1.87",
            "accessLevel" : "Public",
            "annotation" : [ ],
            "codeSystem" : [ ]
         }, {
            "locator" : "12:1-12:136",
            "resultTypeName" : "{urn:hl7-org:elm-types:r1}ValueSet",
            "name" : "Discharged to Health Care Facility for Hospice Care",
            "id" : "http://cts.nlm.nih.gov/fhir/ValueSet/2.16.840.1.113883.3.117.1.7.1.207",
            "accessLevel" : "Public",
            "annotation" : [ ],
            "codeSystem" : [ ]
         }, {
            "locator" : "13:1-13:120",
            "resultTypeName" : "{urn:hl7-org:elm-types:r1}ValueSet",
            "name" : "Discharged to Home for Hospice Care",
            "id" : "http://cts.nlm.nih.gov/fhir/ValueSet/2.16.840.1.113883.3.117.1.7.1.209",
            "accessLevel" : "Public",
            "annotation" : [ ],
            "codeSystem" : [ ]
         }, {
            "locator" : "14:1-14:100",
            "resultTypeName" : "{urn:hl7-org:elm-types:r1}ValueSet",
            "name" : "Ischemic Stroke",
            "id" : "http://cts.nlm.nih.gov/fhir/ValueSet/2.16.840.1.113883.3.117.1.7.1.247",
            "accessLevel" : "Public",
            "annotation" : [ ],
            "codeSystem" : [ ]
         }, {
            "locator" : "15:1-15:112",
            "resultTypeName" : "{urn:hl7-org:elm-types:r1}ValueSet",
            "name" : "Left Against Medical Advice",
            "id" : "http://cts.nlm.nih.gov/fhir/ValueSet/2.16.840.1.113883.3.117.1.7.1.308",
            "accessLevel" : "Public",
            "annotation" : [ ],
            "codeSystem" : [ ]
         }, {
            "locator" : "16:1-16:116",
            "resultTypeName" : "{urn:hl7-org:elm-types:r1}ValueSet",
            "name" : "Nonelective Inpatient Encounter",
            "id" : "http://cts.nlm.nih.gov/fhir/ValueSet/2.16.840.1.113883.3.117.1.7.1.424",
            "accessLevel" : "Public",
            "annotation" : [ ],
            "codeSystem" : [ ]
         }, {
            "locator" : "17:1-17:100",
            "resultTypeName" : "{urn:hl7-org:elm-types:r1}ValueSet",
            "name" : "Patient Expired",
            "id" : "http://cts.nlm.nih.gov/fhir/ValueSet/2.16.840.1.113883.3.117.1.7.1.309",
            "accessLevel" : "Public",
            "annotation" : [ ],
            "codeSystem" : [ ]
         } ]
      },
      "contexts" : {
         "def" : [ {
            "locator" : "22:1-22:15",
            "name" : "Patient",
            "annotation" : [ ]
         } ]
      },
      "statements" : {
         "def" : [ {
            "locator" : "22:1-22:15",
            "name" : "Patient",
            "context" : "Patient",
            "annotation" : [ ],
            "expression" : {
               "type" : "SingletonFrom",
               "annotation" : [ ],
               "signature" : [ ],
               "operand" : {
                  "locator" : "22:1-22:15",
                  "dataType" : "{http://hl7.org/fhir}Patient",
                  "templateId" : "http://hl7.org/fhir/us/qicore/StructureDefinition/qicore-patient",
                  "type" : "Retrieve",
                  "annotation" : [ ],
                  "include" : [ ],
                  "codeFilter" : [ ],
                  "dateFilter" : [ ],
                  "otherFilter" : [ ]
               }
            }
         }, {
            "locator" : "25:1-28:80",
            "name" : "Non Elective Inpatient Encounter With Age",
            "context" : "Patient",
            "accessLevel" : "Public",
            "annotation" : [ ],
            "resultTypeSpecifier" : {
               "type" : "ListTypeSpecifier",
               "annotation" : [ ],
               "elementType" : {
                  "name" : "{http://hl7.org/fhir}Encounter",
                  "type" : "NamedTypeSpecifier",
                  "annotation" : [ ]
               }
            },
            "expression" : {
               "locator" : "26:3-28:80",
               "type" : "Query",
               "annotation" : [ ],
               "resultTypeSpecifier" : {
                  "type" : "ListTypeSpecifier",
                  "annotation" : [ ],
                  "elementType" : {
                     "name" : "{http://hl7.org/fhir}Encounter",
                     "type" : "NamedTypeSpecifier",
                     "annotation" : [ ]
                  }
               },
               "source" : [ {
                  "locator" : "26:3-26:71",
                  "alias" : "NonElectiveEncounter",
                  "annotation" : [ ],
                  "resultTypeSpecifier" : {
                     "type" : "ListTypeSpecifier",
                     "annotation" : [ ],
                     "elementType" : {
                        "name" : "{http://hl7.org/fhir}Encounter",
                        "type" : "NamedTypeSpecifier",
                        "annotation" : [ ]
                     }
                  },
                  "expression" : {
                     "locator" : "26:3-26:50",
                     "dataType" : "{http://hl7.org/fhir}Encounter",
                     "templateId" : "http://hl7.org/fhir/us/qicore/StructureDefinition/qicore-encounter",
                     "codeProperty" : "type",
                     "codeComparator" : "in",
                     "type" : "Retrieve",
                     "annotation" : [ ],
                     "resultTypeSpecifier" : {
                        "type" : "ListTypeSpecifier",
                        "annotation" : [ ],
                        "elementType" : {
                           "name" : "{http://hl7.org/fhir}Encounter",
                           "type" : "NamedTypeSpecifier",
                           "annotation" : [ ]
                        }
                     },
                     "codes" : {
                        "locator" : "26:17-26:49",
                        "resultTypeName" : "{urn:hl7-org:elm-types:r1}ValueSet",
                        "name" : "Nonelective Inpatient Encounter",
                        "preserve" : true,
                        "type" : "ValueSetRef",
                        "annotation" : [ ]
                     },
                     "include" : [ ],
                     "codeFilter" : [ ],
                     "dateFilter" : [ ],
                     "otherFilter" : [ ]
                  }
               } ],
               "let" : [ ],
               "relationship" : [ ],
               "where" : {
                  "locator" : "27:9-28:80",
                  "resultTypeName" : "{urn:hl7-org:elm-types:r1}Boolean",
                  "type" : "And",
                  "annotation" : [ ],
                  "signature" : [ {
                     "name" : "{urn:hl7-org:elm-types:r1}Boolean",
                     "type" : "NamedTypeSpecifier",
                     "annotation" : [ ]
                  }, {
                     "name" : "{urn:hl7-org:elm-types:r1}Boolean",
                     "type" : "NamedTypeSpecifier",
                     "annotation" : [ ]
                  } ],
                  "operand" : [ {
                     "locator" : "27:15-27:81",
                     "resultTypeName" : "{urn:hl7-org:elm-types:r1}Boolean",
                     "type" : "GreaterOrEqual",
                     "annotation" : [ ],
                     "signature" : [ {
                        "name" : "{urn:hl7-org:elm-types:r1}Integer",
                        "type" : "NamedTypeSpecifier",
                        "annotation" : [ ]
                     }, {
                        "name" : "{urn:hl7-org:elm-types:r1}Integer",
                        "type" : "NamedTypeSpecifier",
                        "annotation" : [ ]
                     } ],
                     "operand" : [ {
                        "locator" : "27:15-27:75",
                        "resultTypeName" : "{urn:hl7-org:elm-types:r1}Integer",
                        "precision" : "Year",
                        "type" : "CalculateAgeAt",
                        "annotation" : [ ],
                        "signature" : [ {
                           "name" : "{urn:hl7-org:elm-types:r1}Date",
                           "type" : "NamedTypeSpecifier",
                           "annotation" : [ ]
                        }, {
                           "name" : "{urn:hl7-org:elm-types:r1}Date",
                           "type" : "NamedTypeSpecifier",
                           "annotation" : [ ]
                        } ],
                        "operand" : [ {
                           "path" : "value",
                           "type" : "Property",
                           "annotation" : [ ],
                           "source" : {
                              "path" : "birthDate",
                              "type" : "Property",
                              "annotation" : [ ],
                              "source" : {
                                 "name" : "Patient",
                                 "type" : "ExpressionRef",
                                 "annotation" : [ ]
                              }
                           }
                        }, {
                           "locator" : "27:28-27:73",
                           "resultTypeName" : "{urn:hl7-org:elm-types:r1}Date",
                           "type" : "DateFrom",
                           "annotation" : [ ],
                           "signature" : [ {
                              "name" : "{urn:hl7-org:elm-types:r1}DateTime",
                              "type" : "NamedTypeSpecifier",
                              "annotation" : [ ]
                           } ],
                           "operand" : {
                              "locator" : "27:38-27:73",
                              "resultTypeName" : "{urn:hl7-org:elm-types:r1}DateTime",
                              "type" : "Start",
                              "annotation" : [ ],
                              "signature" : [ {
                                 "type" : "IntervalTypeSpecifier",
                                 "annotation" : [ ],
                                 "pointType" : {
                                    "name" : "{urn:hl7-org:elm-types:r1}DateTime",
                                    "type" : "NamedTypeSpecifier",
                                    "annotation" : [ ]
                                 }
                              } ],
                              "operand" : {
                                 "locator" : "27:47-27:73",
                                 "name" : "ToInterval",
                                 "libraryName" : "FHIRHelpers",
                                 "type" : "FunctionRef",
                                 "annotation" : [ ],
                                 "resultTypeSpecifier" : {
                                    "type" : "IntervalTypeSpecifier",
                                    "annotation" : [ ],
                                    "pointType" : {
                                       "name" : "{urn:hl7-org:elm-types:r1}DateTime",
                                       "type" : "NamedTypeSpecifier",
                                       "annotation" : [ ]
                                    }
                                 },
                                 "signature" : [ {
                                    "name" : "{http://hl7.org/fhir}Period",
                                    "type" : "NamedTypeSpecifier",
                                    "annotation" : [ ]
                                 } ],
                                 "operand" : [ {
                                    "path" : "period",
                                    "scope" : "NonElectiveEncounter",
                                    "type" : "Property",
                                    "annotation" : [ ]
                                 } ]
                              }
                           }
                        } ]
                     }, {
                        "locator" : "27:80-27:81",
                        "resultTypeName" : "{urn:hl7-org:elm-types:r1}Integer",
                        "valueType" : "{urn:hl7-org:elm-types:r1}Integer",
                        "value" : "18",
                        "type" : "Literal",
                        "annotation" : [ ]
                     } ]
                  }, {
                     "locator" : "28:14-28:80",
                     "resultTypeName" : "{urn:hl7-org:elm-types:r1}Boolean",
                     "precision" : "Day",
                     "type" : "In",
                     "annotation" : [ ],
                     "signature" : [ {
                        "name" : "{urn:hl7-org:elm-types:r1}DateTime",
                        "type" : "NamedTypeSpecifier",
                        "annotation" : [ ]
                     }, {
                        "type" : "IntervalTypeSpecifier",
                        "annotation" : [ ],
                        "pointType" : {
                           "name" : "{urn:hl7-org:elm-types:r1}DateTime",
                           "type" : "NamedTypeSpecifier",
                           "annotation" : [ ]
                        }
                     } ],
                     "operand" : [ {
                        "locator" : "28:42-28:45",
                        "type" : "End",
                        "annotation" : [ ],
                        "signature" : [ {
                           "type" : "IntervalTypeSpecifier",
                           "annotation" : [ ],
                           "pointType" : {
                              "name" : "{urn:hl7-org:elm-types:r1}DateTime",
                              "type" : "NamedTypeSpecifier",
                              "annotation" : [ ]
                           }
                        } ],
                        "operand" : {
                           "locator" : "28:14-28:40",
                           "name" : "ToInterval",
                           "libraryName" : "FHIRHelpers",
                           "type" : "FunctionRef",
                           "annotation" : [ ],
                           "resultTypeSpecifier" : {
                              "type" : "IntervalTypeSpecifier",
                              "annotation" : [ ],
                              "pointType" : {
                                 "name" : "{urn:hl7-org:elm-types:r1}DateTime",
                                 "type" : "NamedTypeSpecifier",
                                 "annotation" : [ ]
                              }
                           },
                           "signature" : [ {
                              "name" : "{http://hl7.org/fhir}Period",
                              "type" : "NamedTypeSpecifier",
                              "annotation" : [ ]
                           } ],
                           "operand" : [ {
                              "path" : "period",
                              "scope" : "NonElectiveEncounter",
                              "type" : "Property",
                              "annotation" : [ ]
                           } ]
                        }
                     }, {
                        "locator" : "28:61-28:80",
                        "name" : "Measurement Period",
                        "type" : "ParameterRef",
                        "annotation" : [ ],
                        "resultTypeSpecifier" : {
                           "type" : "IntervalTypeSpecifier",
                           "annotation" : [ ],
                           "pointType" : {
                              "name" : "{urn:hl7-org:elm-types:r1}DateTime",
                              "type" : "NamedTypeSpecifier",
                              "annotation" : [ ]
                           }
                        }
                     } ]
                  } ]
               }
            }
         }, {
            "locator" : "31:1-33:84",
            "name" : "Ischemic Stroke Encounter",
            "context" : "Patient",
            "accessLevel" : "Public",
            "annotation" : [ ],
            "resultTypeSpecifier" : {
               "type" : "ListTypeSpecifier",
               "annotation" : [ ],
               "elementType" : {
                  "name" : "{http://hl7.org/fhir}Encounter",
                  "type" : "NamedTypeSpecifier",
                  "annotation" : [ ]
               }
            },
            "expression" : {
               "locator" : "32:3-33:84",
               "type" : "Query",
               "annotation" : [ ],
               "resultTypeSpecifier" : {
                  "type" : "ListTypeSpecifier",
                  "annotation" : [ ],
                  "elementType" : {
                     "name" : "{http://hl7.org/fhir}Encounter",
                     "type" : "NamedTypeSpecifier",
                     "annotation" : [ ]
                  }
               },
               "source" : [ {
                  "locator" : "32:3-32:73",
                  "alias" : "NonElectiveEncounterWithAge",
                  "annotation" : [ ],
                  "resultTypeSpecifier" : {
                     "type" : "ListTypeSpecifier",
                     "annotation" : [ ],
                     "elementType" : {
                        "name" : "{http://hl7.org/fhir}Encounter",
                        "type" : "NamedTypeSpecifier",
                        "annotation" : [ ]
                     }
                  },
                  "expression" : {
                     "locator" : "32:3-32:45",
                     "name" : "Non Elective Inpatient Encounter With Age",
                     "type" : "ExpressionRef",
                     "annotation" : [ ],
                     "resultTypeSpecifier" : {
                        "type" : "ListTypeSpecifier",
                        "annotation" : [ ],
                        "elementType" : {
                           "name" : "{http://hl7.org/fhir}Encounter",
                           "type" : "NamedTypeSpecifier",
                           "annotation" : [ ]
                        }
                     }
                  }
               } ],
               "let" : [ ],
               "relationship" : [ ],
               "where" : {
                  "locator" : "33:5-33:84",
                  "resultTypeName" : "{urn:hl7-org:elm-types:r1}Boolean",
                  "type" : "InValueSet",
                  "annotation" : [ ],
                  "signature" : [ {
                     "name" : "{urn:hl7-org:elm-types:r1}Concept",
                     "type" : "NamedTypeSpecifier",
                     "annotation" : [ ]
                  } ],
                  "code" : {
                     "locator" : "33:11-33:63",
                     "resultTypeName" : "{urn:hl7-org:elm-types:r1}Concept",
                     "name" : "ToConcept",
                     "libraryName" : "FHIRHelpers",
                     "type" : "FunctionRef",
                     "annotation" : [ ],
                     "signature" : [ ],
                     "operand" : [ {
                        "path" : "code",
                        "type" : "Property",
                        "annotation" : [ ],
                        "source" : {
                           "locator" : "33:11-33:58",
                           "resultTypeName" : "{http://hl7.org/fhir}Condition",
                           "name" : "principalDiagnosis",
                           "libraryName" : "CQMCommon",
                           "type" : "FunctionRef",
                           "annotation" : [ ],
                           "signature" : [ {
                              "name" : "{http://hl7.org/fhir}Encounter",
                              "type" : "NamedTypeSpecifier",
                              "annotation" : [ ]
                           } ],
                           "operand" : [ {
                              "locator" : "33:11-33:37",
                              "resultTypeName" : "{http://hl7.org/fhir}Encounter",
                              "name" : "NonElectiveEncounterWithAge",
                              "type" : "AliasRef",
                              "annotation" : [ ]
                           } ]
                        }
                     } ]
                  },
                  "valueset" : {
                     "locator" : "33:68-33:84",
                     "resultTypeName" : "{urn:hl7-org:elm-types:r1}ValueSet",
                     "name" : "Ischemic Stroke",
                     "preserve" : true,
                     "annotation" : [ ]
                  }
               }
            }
         }, {
            "locator" : "35:1-42:71",
            "name" : "Ischemic Stroke Encounters With Discharge Disposition",
            "context" : "Patient",
            "accessLevel" : "Public",
            "annotation" : [ ],
            "resultTypeSpecifier" : {
               "type" : "ListTypeSpecifier",
               "annotation" : [ ],
               "elementType" : {
                  "name" : "{http://hl7.org/fhir}Encounter",
                  "type" : "NamedTypeSpecifier",
                  "annotation" : [ ]
               }
            },
            "expression" : {
               "locator" : "36:3-42:71",
               "type" : "Query",
               "annotation" : [ ],
               "resultTypeSpecifier" : {
                  "type" : "ListTypeSpecifier",
                  "annotation" : [ ],
                  "elementType" : {
                     "name" : "{http://hl7.org/fhir}Encounter",
                     "type" : "NamedTypeSpecifier",
                     "annotation" : [ ]
                  }
               },
               "source" : [ {
                  "locator" : "36:3-36:53",
                  "alias" : "IschemicStrokeEncounter",
                  "annotation" : [ ],
                  "resultTypeSpecifier" : {
                     "type" : "ListTypeSpecifier",
                     "annotation" : [ ],
                     "elementType" : {
                        "name" : "{http://hl7.org/fhir}Encounter",
                        "type" : "NamedTypeSpecifier",
                        "annotation" : [ ]
                     }
                  },
                  "expression" : {
                     "locator" : "36:3-36:29",
                     "name" : "Ischemic Stroke Encounter",
                     "type" : "ExpressionRef",
                     "annotation" : [ ],
                     "resultTypeSpecifier" : {
                        "type" : "ListTypeSpecifier",
                        "annotation" : [ ],
                        "elementType" : {
                           "name" : "{http://hl7.org/fhir}Encounter",
                           "type" : "NamedTypeSpecifier",
                           "annotation" : [ ]
                        }
                     }
                  }
               } ],
               "let" : [ {
                  "locator" : "37:7-37:77",
                  "resultTypeName" : "{urn:hl7-org:elm-types:r1}Concept",
                  "identifier" : "DischDisp",
                  "annotation" : [ ],
                  "expression" : {
                     "locator" : "37:18-37:77",
                     "resultTypeName" : "{urn:hl7-org:elm-types:r1}Concept",
                     "name" : "ToConcept",
                     "libraryName" : "FHIRHelpers",
                     "type" : "FunctionRef",
                     "annotation" : [ ],
                     "signature" : [ ],
                     "operand" : [ {
                        "path" : "dischargeDisposition",
                        "type" : "Property",
                        "annotation" : [ ],
                        "source" : {
                           "locator" : "37:18-37:56",
                           "resultTypeName" : "{http://hl7.org/fhir}Encounter.Hospitalization",
                           "path" : "hospitalization",
                           "scope" : "IschemicStrokeEncounter",
                           "type" : "Property",
                           "annotation" : [ ]
                        }
                     } ]
                  }
               } ],
               "relationship" : [ ],
               "where" : {
                  "locator" : "38:4-42:71",
                  "resultTypeName" : "{urn:hl7-org:elm-types:r1}Boolean",
                  "type" : "Or",
                  "annotation" : [ ],
                  "signature" : [ {
                     "name" : "{urn:hl7-org:elm-types:r1}Boolean",
                     "type" : "NamedTypeSpecifier",
                     "annotation" : [ ]
                  }, {
                     "name" : "{urn:hl7-org:elm-types:r1}Boolean",
                     "type" : "NamedTypeSpecifier",
                     "annotation" : [ ]
                  } ],
                  "operand" : [ {
                     "locator" : "38:11-41:55",
                     "resultTypeName" : "{urn:hl7-org:elm-types:r1}Boolean",
                     "type" : "Or",
                     "annotation" : [ ],
                     "signature" : [ {
                        "name" : "{urn:hl7-org:elm-types:r1}Boolean",
                        "type" : "NamedTypeSpecifier",
                        "annotation" : [ ]
                     }, {
                        "name" : "{urn:hl7-org:elm-types:r1}Boolean",
                        "type" : "NamedTypeSpecifier",
                        "annotation" : [ ]
                     } ],
                     "operand" : [ {
                        "locator" : "38:11-40:35",
                        "resultTypeName" : "{urn:hl7-org:elm-types:r1}Boolean",
                        "type" : "Or",
                        "annotation" : [ ],
                        "signature" : [ {
                           "name" : "{urn:hl7-org:elm-types:r1}Boolean",
                           "type" : "NamedTypeSpecifier",
                           "annotation" : [ ]
                        }, {
                           "name" : "{urn:hl7-org:elm-types:r1}Boolean",
                           "type" : "NamedTypeSpecifier",
                           "annotation" : [ ]
                        } ],
                        "operand" : [ {
                           "locator" : "38:11-39:47",
                           "resultTypeName" : "{urn:hl7-org:elm-types:r1}Boolean",
                           "type" : "Or",
                           "annotation" : [ ],
                           "signature" : [ {
                              "name" : "{urn:hl7-org:elm-types:r1}Boolean",
                              "type" : "NamedTypeSpecifier",
                              "annotation" : [ ]
                           }, {
                              "name" : "{urn:hl7-org:elm-types:r1}Boolean",
                              "type" : "NamedTypeSpecifier",
                              "annotation" : [ ]
                           } ],
                           "operand" : [ {
                              "locator" : "38:11-38:57",
                              "resultTypeName" : "{urn:hl7-org:elm-types:r1}Boolean",
                              "type" : "InValueSet",
                              "annotation" : [ ],
                              "signature" : [ {
                                 "name" : "{urn:hl7-org:elm-types:r1}Concept",
                                 "type" : "NamedTypeSpecifier",
                                 "annotation" : [ ]
                              } ],
                              "code" : {
                                 "locator" : "38:11-38:19",
                                 "resultTypeName" : "{urn:hl7-org:elm-types:r1}Concept",
                                 "name" : "DischDisp",
                                 "type" : "QueryLetRef",
                                 "annotation" : [ ]
                              },
                              "valueset" : {
                                 "locator" : "38:24-38:57",
                                 "resultTypeName" : "{urn:hl7-org:elm-types:r1}ValueSet",
                                 "name" : "Discharge To Acute Care Facility",
                                 "preserve" : true,
                                 "annotation" : [ ]
                              }
                           }, {
                              "locator" : "39:6-39:47",
                              "resultTypeName" : "{urn:hl7-org:elm-types:r1}Boolean",
                              "type" : "InValueSet",
                              "annotation" : [ ],
                              "signature" : [ {
                                 "name" : "{urn:hl7-org:elm-types:r1}Concept",
                                 "type" : "NamedTypeSpecifier",
                                 "annotation" : [ ]
                              } ],
                              "code" : {
                                 "locator" : "39:6-39:14",
                                 "resultTypeName" : "{urn:hl7-org:elm-types:r1}Concept",
                                 "name" : "DischDisp",
                                 "type" : "QueryLetRef",
                                 "annotation" : [ ]
                              },
                              "valueset" : {
                                 "locator" : "39:19-39:47",
                                 "resultTypeName" : "{urn:hl7-org:elm-types:r1}ValueSet",
                                 "name" : "Left Against Medical Advice",
                                 "preserve" : true,
                                 "annotation" : [ ]
                              }
                           } ]
                        }, {
                           "locator" : "40:6-40:35",
                           "resultTypeName" : "{urn:hl7-org:elm-types:r1}Boolean",
                           "type" : "InValueSet",
                           "annotation" : [ ],
                           "signature" : [ {
                              "name" : "{urn:hl7-org:elm-types:r1}Concept",
                              "type" : "NamedTypeSpecifier",
                              "annotation" : [ ]
                           } ],
                           "code" : {
                              "locator" : "40:6-40:14",
                              "resultTypeName" : "{urn:hl7-org:elm-types:r1}Concept",
                              "name" : "DischDisp",
                              "type" : "QueryLetRef",
                              "annotation" : [ ]
                           },
                           "valueset" : {
                              "locator" : "40:19-40:35",
                              "resultTypeName" : "{urn:hl7-org:elm-types:r1}ValueSet",
                              "name" : "Patient Expired",
                              "preserve" : true,
                              "annotation" : [ ]
                           }
                        } ]
                     }, {
                        "locator" : "41:6-41:55",
                        "resultTypeName" : "{urn:hl7-org:elm-types:r1}Boolean",
                        "type" : "InValueSet",
                        "annotation" : [ ],
                        "signature" : [ {
                           "name" : "{urn:hl7-org:elm-types:r1}Concept",
                           "type" : "NamedTypeSpecifier",
                           "annotation" : [ ]
                        } ],
                        "code" : {
                           "locator" : "41:6-41:14",
                           "resultTypeName" : "{urn:hl7-org:elm-types:r1}Concept",
                           "name" : "DischDisp",
                           "type" : "QueryLetRef",
                           "annotation" : [ ]
                        },
                        "valueset" : {
                           "locator" : "41:19-41:55",
                           "resultTypeName" : "{urn:hl7-org:elm-types:r1}ValueSet",
                           "name" : "Discharged to Home for Hospice Care",
                           "preserve" : true,
                           "annotation" : [ ]
                        }
                     } ]
                  }, {
                     "locator" : "42:6-42:71",
                     "resultTypeName" : "{urn:hl7-org:elm-types:r1}Boolean",
                     "type" : "InValueSet",
                     "annotation" : [ ],
                     "signature" : [ {
                        "name" : "{urn:hl7-org:elm-types:r1}Concept",
                        "type" : "NamedTypeSpecifier",
                        "annotation" : [ ]
                     } ],
                     "code" : {
                        "locator" : "42:6-42:14",
                        "resultTypeName" : "{urn:hl7-org:elm-types:r1}Concept",
                        "name" : "DischDisp",
                        "type" : "QueryLetRef",
                        "annotation" : [ ]
                     },
                     "valueset" : {
                        "locator" : "42:19-42:71",
                        "resultTypeName" : "{urn:hl7-org:elm-types:r1}ValueSet",
                        "name" : "Discharged to Health Care Facility for Hospice Care",
                        "preserve" : true,
                        "annotation" : [ ]
                     }
                  } ]
               }
            }
         }, {
            "locator" : "54:1-62:3",
            "name" : "Intervention Comfort Measures",
            "context" : "Patient",
            "accessLevel" : "Public",
            "annotation" : [ ],
            "resultTypeSpecifier" : {
               "type" : "ListTypeSpecifier",
               "annotation" : [ ],
               "elementType" : {
                  "type" : "ChoiceTypeSpecifier",
                  "annotation" : [ ],
                  "choice" : [ {
                     "name" : "{http://hl7.org/fhir}ServiceRequest",
                     "type" : "NamedTypeSpecifier",
                     "annotation" : [ ]
                  }, {
                     "name" : "{http://hl7.org/fhir}Procedure",
                     "type" : "NamedTypeSpecifier",
                     "annotation" : [ ]
                  } ]
               }
            },
            "expression" : {
               "locator" : "55:3-62:3",
               "type" : "Union",
               "annotation" : [ ],
               "resultTypeSpecifier" : {
                  "type" : "ListTypeSpecifier",
                  "annotation" : [ ],
                  "elementType" : {
                     "type" : "ChoiceTypeSpecifier",
                     "annotation" : [ ],
                     "choice" : [ {
                        "name" : "{http://hl7.org/fhir}ServiceRequest",
                        "type" : "NamedTypeSpecifier",
                        "annotation" : [ ]
                     }, {
                        "name" : "{http://hl7.org/fhir}Procedure",
                        "type" : "NamedTypeSpecifier",
                        "annotation" : [ ]
                     } ]
                  }
               },
               "signature" : [ {
                  "type" : "ListTypeSpecifier",
                  "annotation" : [ ],
                  "elementType" : {
                     "type" : "ChoiceTypeSpecifier",
                     "annotation" : [ ],
                     "choice" : [ {
                        "name" : "{http://hl7.org/fhir}ServiceRequest",
                        "type" : "NamedTypeSpecifier",
                        "annotation" : [ ]
                     }, {
                        "name" : "{http://hl7.org/fhir}Procedure",
                        "type" : "NamedTypeSpecifier",
                        "annotation" : [ ]
                     } ]
                  }
               }, {
                  "type" : "ListTypeSpecifier",
                  "annotation" : [ ],
                  "elementType" : {
                     "type" : "ChoiceTypeSpecifier",
                     "annotation" : [ ],
                     "choice" : [ {
                        "name" : "{http://hl7.org/fhir}ServiceRequest",
                        "type" : "NamedTypeSpecifier",
                        "annotation" : [ ]
                     }, {
                        "name" : "{http://hl7.org/fhir}Procedure",
                        "type" : "NamedTypeSpecifier",
                        "annotation" : [ ]
                     } ]
                  }
               } ],
               "operand" : [ {
                  "type" : "As",
                  "annotation" : [ ],
                  "signature" : [ ],
                  "operand" : {
                     "locator" : "55:3-59:3",
                     "type" : "Query",
                     "annotation" : [ ],
                     "resultTypeSpecifier" : {
                        "type" : "ListTypeSpecifier",
                        "annotation" : [ ],
                        "elementType" : {
                           "name" : "{http://hl7.org/fhir}ServiceRequest",
                           "type" : "NamedTypeSpecifier",
                           "annotation" : [ ]
                        }
                     },
                     "source" : [ {
                        "locator" : "55:5-55:53",
                        "alias" : "SR",
                        "annotation" : [ ],
                        "resultTypeSpecifier" : {
                           "type" : "ListTypeSpecifier",
                           "annotation" : [ ],
                           "elementType" : {
                              "name" : "{http://hl7.org/fhir}ServiceRequest",
                              "type" : "NamedTypeSpecifier",
                              "annotation" : [ ]
                           }
                        },
                        "expression" : {
                           "locator" : "55:5-55:50",
                           "dataType" : "{http://hl7.org/fhir}ServiceRequest",
                           "templateId" : "http://hl7.org/fhir/us/qicore/StructureDefinition/qicore-servicerequest",
                           "codeProperty" : "code",
                           "codeComparator" : "in",
                           "type" : "Retrieve",
                           "annotation" : [ ],
                           "resultTypeSpecifier" : {
                              "type" : "ListTypeSpecifier",
                              "annotation" : [ ],
                              "elementType" : {
                                 "name" : "{http://hl7.org/fhir}ServiceRequest",
                                 "type" : "NamedTypeSpecifier",
                                 "annotation" : [ ]
                              }
                           },
                           "codes" : {
                              "locator" : "55:32-55:49",
                              "resultTypeName" : "{urn:hl7-org:elm-types:r1}ValueSet",
                              "name" : "Comfort Measures",
                              "preserve" : true,
                              "type" : "ValueSetRef",
                              "annotation" : [ ]
                           },
                           "include" : [ ],
                           "codeFilter" : [ ],
                           "dateFilter" : [ ],
                           "otherFilter" : [ ]
                        }
                     } ],
                     "let" : [ ],
                     "relationship" : [ ],
                     "where" : {
                        "locator" : "56:5-58:37",
                        "resultTypeName" : "{urn:hl7-org:elm-types:r1}Boolean",
                        "type" : "And",
                        "annotation" : [ ],
                        "signature" : [ {
                           "name" : "{urn:hl7-org:elm-types:r1}Boolean",
                           "type" : "NamedTypeSpecifier",
                           "annotation" : [ ]
                        }, {
                           "name" : "{urn:hl7-org:elm-types:r1}Boolean",
                           "type" : "NamedTypeSpecifier",
                           "annotation" : [ ]
                        } ],
                        "operand" : [ {
                           "locator" : "56:11-57:102",
                           "resultTypeName" : "{urn:hl7-org:elm-types:r1}Boolean",
                           "type" : "And",
                           "annotation" : [ ],
                           "signature" : [ {
                              "name" : "{urn:hl7-org:elm-types:r1}Boolean",
                              "type" : "NamedTypeSpecifier",
                              "annotation" : [ ]
                           }, {
                              "name" : "{urn:hl7-org:elm-types:r1}Boolean",
                              "type" : "NamedTypeSpecifier",
                              "annotation" : [ ]
                           } ],
                           "operand" : [ {
                              "locator" : "56:11-56:59",
                              "resultTypeName" : "{urn:hl7-org:elm-types:r1}Boolean",
                              "type" : "In",
                              "annotation" : [ ],
                              "signature" : [ {
                                 "name" : "{urn:hl7-org:elm-types:r1}String",
                                 "type" : "NamedTypeSpecifier",
                                 "annotation" : [ ]
                              }, {
                                 "type" : "ListTypeSpecifier",
                                 "annotation" : [ ],
                                 "elementType" : {
                                    "name" : "{urn:hl7-org:elm-types:r1}String",
                                    "type" : "NamedTypeSpecifier",
                                    "annotation" : [ ]
                                 }
                              } ],
                              "operand" : [ {
                                 "locator" : "56:11-56:19",
                                 "resultTypeName" : "{http://hl7.org/fhir}ServiceRequestStatus",
                                 "path" : "value",
                                 "type" : "Property",
                                 "annotation" : [ ],
                                 "source" : {
                                    "path" : "status",
                                    "scope" : "SR",
                                    "type" : "Property",
                                    "annotation" : [ ]
                                 }
                              }, {
                                 "locator" : "56:24-56:59",
                                 "type" : "List",
                                 "annotation" : [ ],
                                 "resultTypeSpecifier" : {
                                    "type" : "ListTypeSpecifier",
                                    "annotation" : [ ],
                                    "elementType" : {
                                       "name" : "{urn:hl7-org:elm-types:r1}String",
                                       "type" : "NamedTypeSpecifier",
                                       "annotation" : [ ]
                                    }
                                 },
                                 "element" : [ {
                                    "locator" : "56:26-56:33",
                                    "resultTypeName" : "{urn:hl7-org:elm-types:r1}String",
                                    "valueType" : "{urn:hl7-org:elm-types:r1}String",
                                    "value" : "active",
                                    "type" : "Literal",
                                    "annotation" : [ ]
                                 }, {
                                    "locator" : "56:36-56:46",
                                    "resultTypeName" : "{urn:hl7-org:elm-types:r1}String",
                                    "valueType" : "{urn:hl7-org:elm-types:r1}String",
                                    "value" : "completed",
                                    "type" : "Literal",
                                    "annotation" : [ ]
                                 }, {
                                    "locator" : "56:49-56:57",
                                    "resultTypeName" : "{urn:hl7-org:elm-types:r1}String",
                                    "valueType" : "{urn:hl7-org:elm-types:r1}String",
                                    "value" : "on-hold",
                                    "type" : "Literal",
                                    "annotation" : [ ]
                                 } ]
                              } ]
                           }, {
                              "locator" : "57:11-57:102",
                              "resultTypeName" : "{urn:hl7-org:elm-types:r1}Boolean",
                              "type" : "In",
                              "annotation" : [ ],
                              "signature" : [ {
                                 "name" : "{urn:hl7-org:elm-types:r1}String",
                                 "type" : "NamedTypeSpecifier",
                                 "annotation" : [ ]
                              }, {
                                 "type" : "ListTypeSpecifier",
                                 "annotation" : [ ],
                                 "elementType" : {
                                    "name" : "{urn:hl7-org:elm-types:r1}String",
                                    "type" : "NamedTypeSpecifier",
                                    "annotation" : [ ]
                                 }
                              } ],
                              "operand" : [ {
                                 "locator" : "57:11-57:19",
                                 "resultTypeName" : "{http://hl7.org/fhir}ServiceRequestIntent",
                                 "path" : "value",
                                 "type" : "Property",
                                 "annotation" : [ ],
                                 "source" : {
                                    "path" : "intent",
                                    "scope" : "SR",
                                    "type" : "Property",
                                    "annotation" : [ ]
                                 }
                              }, {
                                 "locator" : "57:24-57:102",
                                 "type" : "List",
                                 "annotation" : [ ],
                                 "resultTypeSpecifier" : {
                                    "type" : "ListTypeSpecifier",
                                    "annotation" : [ ],
                                    "elementType" : {
                                       "name" : "{urn:hl7-org:elm-types:r1}String",
                                       "type" : "NamedTypeSpecifier",
                                       "annotation" : [ ]
                                    }
                                 },
                                 "element" : [ {
                                    "locator" : "57:26-57:32",
                                    "resultTypeName" : "{urn:hl7-org:elm-types:r1}String",
                                    "valueType" : "{urn:hl7-org:elm-types:r1}String",
                                    "value" : "order",
                                    "type" : "Literal",
                                    "annotation" : [ ]
                                 }, {
                                    "locator" : "57:35-57:50",
                                    "resultTypeName" : "{urn:hl7-org:elm-types:r1}String",
                                    "valueType" : "{urn:hl7-org:elm-types:r1}String",
                                    "value" : "original-order",
                                    "type" : "Literal",
                                    "annotation" : [ ]
                                 }, {
                                    "locator" : "57:53-57:66",
                                    "resultTypeName" : "{urn:hl7-org:elm-types:r1}String",
                                    "valueType" : "{urn:hl7-org:elm-types:r1}String",
                                    "value" : "reflex-order",
                                    "type" : "Literal",
                                    "annotation" : [ ]
                                 }, {
                                    "locator" : "57:69-57:82",
                                    "resultTypeName" : "{urn:hl7-org:elm-types:r1}String",
                                    "valueType" : "{urn:hl7-org:elm-types:r1}String",
                                    "value" : "filler-order",
                                    "type" : "Literal",
                                    "annotation" : [ ]
                                 }, {
                                    "locator" : "57:85-57:100",
                                    "resultTypeName" : "{urn:hl7-org:elm-types:r1}String",
                                    "valueType" : "{urn:hl7-org:elm-types:r1}String",
                                    "value" : "instance-order",
                                    "type" : "Literal",
                                    "annotation" : [ ]
                                 } ]
                              } ]
                           } ]
                        }, {
                           "locator" : "58:11-58:37",
                           "resultTypeName" : "{urn:hl7-org:elm-types:r1}Boolean",
                           "type" : "Not",
                           "annotation" : [ ],
                           "signature" : [ {
                              "name" : "{urn:hl7-org:elm-types:r1}Boolean",
                              "type" : "NamedTypeSpecifier",
                              "annotation" : [ ]
                           } ],
                           "operand" : {
                              "locator" : "58:11-58:37",
                              "resultTypeName" : "{urn:hl7-org:elm-types:r1}Boolean",
                              "type" : "IsTrue",
                              "annotation" : [ ],
                              "signature" : [ {
                                 "name" : "{urn:hl7-org:elm-types:r1}Boolean",
                                 "type" : "NamedTypeSpecifier",
                                 "annotation" : [ ]
                              } ],
                              "operand" : {
                                 "locator" : "58:11-58:25",
                                 "resultTypeName" : "{urn:hl7-org:elm-types:r1}Boolean",
                                 "path" : "value",
                                 "type" : "Property",
                                 "annotation" : [ ],
                                 "source" : {
                                    "path" : "doNotPerform",
                                    "scope" : "SR",
                                    "type" : "Property",
                                    "annotation" : [ ]
                                 }
                              }
                           }
                        } ]
                     }
                  },
                  "asTypeSpecifier" : {
                     "type" : "ListTypeSpecifier",
                     "annotation" : [ ],
                     "elementType" : {
                        "type" : "ChoiceTypeSpecifier",
                        "annotation" : [ ],
                        "choice" : [ {
                           "name" : "{http://hl7.org/fhir}ServiceRequest",
                           "type" : "NamedTypeSpecifier",
                           "annotation" : [ ]
                        }, {
                           "name" : "{http://hl7.org/fhir}Procedure",
                           "type" : "NamedTypeSpecifier",
                           "annotation" : [ ]
                        } ]
                     }
                  }
               }, {
                  "type" : "As",
                  "annotation" : [ ],
                  "signature" : [ ],
                  "operand" : {
                     "locator" : "60:9-62:3",
                     "type" : "Query",
                     "annotation" : [ ],
                     "resultTypeSpecifier" : {
                        "type" : "ListTypeSpecifier",
                        "annotation" : [ ],
                        "elementType" : {
                           "name" : "{http://hl7.org/fhir}Procedure",
                           "type" : "NamedTypeSpecifier",
                           "annotation" : [ ]
                        }
                     },
                     "source" : [ {
                        "locator" : "60:11-60:65",
                        "alias" : "InterventionPerformed",
                        "annotation" : [ ],
                        "resultTypeSpecifier" : {
                           "type" : "ListTypeSpecifier",
                           "annotation" : [ ],
                           "elementType" : {
                              "name" : "{http://hl7.org/fhir}Procedure",
                              "type" : "NamedTypeSpecifier",
                              "annotation" : [ ]
                           }
                        },
                        "expression" : {
                           "locator" : "60:11-60:43",
                           "dataType" : "{http://hl7.org/fhir}Procedure",
                           "templateId" : "http://hl7.org/fhir/us/qicore/StructureDefinition/qicore-procedure",
                           "codeProperty" : "code",
                           "codeComparator" : "in",
                           "type" : "Retrieve",
                           "annotation" : [ ],
                           "resultTypeSpecifier" : {
                              "type" : "ListTypeSpecifier",
                              "annotation" : [ ],
                              "elementType" : {
                                 "name" : "{http://hl7.org/fhir}Procedure",
                                 "type" : "NamedTypeSpecifier",
                                 "annotation" : [ ]
                              }
                           },
                           "codes" : {
                              "locator" : "60:25-60:42",
                              "resultTypeName" : "{urn:hl7-org:elm-types:r1}ValueSet",
                              "name" : "Comfort Measures",
                              "preserve" : true,
                              "type" : "ValueSetRef",
                              "annotation" : [ ]
                           },
                           "include" : [ ],
                           "codeFilter" : [ ],
                           "dateFilter" : [ ],
                           "otherFilter" : [ ]
                        }
                     } ],
                     "let" : [ ],
                     "relationship" : [ ],
                     "where" : {
                        "locator" : "61:9-61:76",
                        "resultTypeName" : "{urn:hl7-org:elm-types:r1}Boolean",
                        "type" : "In",
                        "annotation" : [ ],
                        "signature" : [ {
                           "name" : "{urn:hl7-org:elm-types:r1}String",
                           "type" : "NamedTypeSpecifier",
                           "annotation" : [ ]
                        }, {
                           "type" : "ListTypeSpecifier",
                           "annotation" : [ ],
                           "elementType" : {
                              "name" : "{urn:hl7-org:elm-types:r1}String",
                              "type" : "NamedTypeSpecifier",
                              "annotation" : [ ]
                           }
                        } ],
                        "operand" : [ {
                           "locator" : "61:15-61:42",
                           "resultTypeName" : "{urn:hl7-org:elm-types:r1}String",
                           "path" : "value",
                           "type" : "Property",
                           "annotation" : [ ],
                           "source" : {
                              "path" : "status",
                              "scope" : "InterventionPerformed",
                              "type" : "Property",
                              "annotation" : [ ]
                           }
                        }, {
                           "locator" : "61:47-61:76",
                           "type" : "List",
                           "annotation" : [ ],
                           "resultTypeSpecifier" : {
                              "type" : "ListTypeSpecifier",
                              "annotation" : [ ],
                              "elementType" : {
                                 "name" : "{urn:hl7-org:elm-types:r1}String",
                                 "type" : "NamedTypeSpecifier",
                                 "annotation" : [ ]
                              }
                           },
                           "element" : [ {
                              "locator" : "61:49-61:59",
                              "resultTypeName" : "{urn:hl7-org:elm-types:r1}String",
                              "valueType" : "{urn:hl7-org:elm-types:r1}String",
                              "value" : "completed",
                              "type" : "Literal",
                              "annotation" : [ ]
                           }, {
                              "locator" : "61:62-61:74",
                              "resultTypeName" : "{urn:hl7-org:elm-types:r1}String",
                              "valueType" : "{urn:hl7-org:elm-types:r1}String",
                              "value" : "in-progress",
                              "type" : "Literal",
                              "annotation" : [ ]
                           } ]
                        } ]
                     }
                  },
                  "asTypeSpecifier" : {
                     "type" : "ListTypeSpecifier",
                     "annotation" : [ ],
                     "elementType" : {
                        "type" : "ChoiceTypeSpecifier",
                        "annotation" : [ ],
                        "choice" : [ {
                           "name" : "{http://hl7.org/fhir}ServiceRequest",
                           "type" : "NamedTypeSpecifier",
                           "annotation" : [ ]
                        }, {
                           "name" : "{http://hl7.org/fhir}Procedure",
                           "type" : "NamedTypeSpecifier",
                           "annotation" : [ ]
                        } ]
                     }
                  }
               } ]
            }
         }, {
            "locator" : "44:1-47:162",
            "name" : "Comfort Measures During Hospitalization",
            "context" : "Patient",
            "accessLevel" : "Public",
            "annotation" : [ ],
            "resultTypeSpecifier" : {
               "type" : "ListTypeSpecifier",
               "annotation" : [ ],
               "elementType" : {
                  "name" : "{http://hl7.org/fhir}Encounter",
                  "type" : "NamedTypeSpecifier",
                  "annotation" : [ ]
               }
            },
            "expression" : {
               "locator" : "45:3-47:162",
               "type" : "Query",
               "annotation" : [ ],
               "resultTypeSpecifier" : {
                  "type" : "ListTypeSpecifier",
                  "annotation" : [ ],
                  "elementType" : {
                     "name" : "{http://hl7.org/fhir}Encounter",
                     "type" : "NamedTypeSpecifier",
                     "annotation" : [ ]
                  }
               },
               "source" : [ {
                  "locator" : "45:3-45:53",
                  "alias" : "IschemicStrokeEncounter",
                  "annotation" : [ ],
                  "resultTypeSpecifier" : {
                     "type" : "ListTypeSpecifier",
                     "annotation" : [ ],
                     "elementType" : {
                        "name" : "{http://hl7.org/fhir}Encounter",
                        "type" : "NamedTypeSpecifier",
                        "annotation" : [ ]
                     }
                  },
                  "expression" : {
                     "locator" : "45:3-45:29",
                     "name" : "Ischemic Stroke Encounter",
                     "type" : "ExpressionRef",
                     "annotation" : [ ],
                     "resultTypeSpecifier" : {
                        "type" : "ListTypeSpecifier",
                        "annotation" : [ ],
                        "elementType" : {
                           "name" : "{http://hl7.org/fhir}Encounter",
                           "type" : "NamedTypeSpecifier",
                           "annotation" : [ ]
                        }
                     }
                  }
               } ],
               "let" : [ ],
               "relationship" : [ {
                  "locator" : "46:5-47:162",
                  "alias" : "ComfortMeasure",
                  "type" : "With",
                  "annotation" : [ ],
                  "resultTypeSpecifier" : {
                     "type" : "ListTypeSpecifier",
                     "annotation" : [ ],
                     "elementType" : {
                        "type" : "ChoiceTypeSpecifier",
                        "annotation" : [ ],
                        "choice" : [ {
                           "name" : "{http://hl7.org/fhir}ServiceRequest",
                           "type" : "NamedTypeSpecifier",
                           "annotation" : [ ]
                        }, {
                           "name" : "{http://hl7.org/fhir}Procedure",
                           "type" : "NamedTypeSpecifier",
                           "annotation" : [ ]
                        } ]
                     }
                  },
                  "expression" : {
                     "locator" : "46:10-46:40",
                     "name" : "Intervention Comfort Measures",
                     "type" : "ExpressionRef",
                     "annotation" : [ ],
                     "resultTypeSpecifier" : {
                        "type" : "ListTypeSpecifier",
                        "annotation" : [ ],
                        "elementType" : {
                           "type" : "ChoiceTypeSpecifier",
                           "annotation" : [ ],
                           "choice" : [ {
                              "name" : "{http://hl7.org/fhir}ServiceRequest",
                              "type" : "NamedTypeSpecifier",
                              "annotation" : [ ]
                           }, {
                              "name" : "{http://hl7.org/fhir}Procedure",
                              "type" : "NamedTypeSpecifier",
                              "annotation" : [ ]
                           } ]
                        }
                     }
                  },
                  "suchThat" : {
                     "locator" : "47:16-47:162",
                     "resultTypeName" : "{urn:hl7-org:elm-types:r1}Boolean",
                     "type" : "In",
                     "annotation" : [ ],
                     "signature" : [ {
                        "name" : "{urn:hl7-org:elm-types:r1}DateTime",
                        "type" : "NamedTypeSpecifier",
                        "annotation" : [ ]
                     }, {
                        "type" : "IntervalTypeSpecifier",
                        "annotation" : [ ],
                        "pointType" : {
                           "name" : "{urn:hl7-org:elm-types:r1}DateTime",
                           "type" : "NamedTypeSpecifier",
                           "annotation" : [ ]
                        }
                     } ],
                     "operand" : [ {
                        "locator" : "47:16-47:98",
                        "resultTypeName" : "{urn:hl7-org:elm-types:r1}DateTime",
                        "type" : "Coalesce",
                        "annotation" : [ ],
                        "signature" : [ {
                           "name" : "{urn:hl7-org:elm-types:r1}DateTime",
                           "type" : "NamedTypeSpecifier",
                           "annotation" : [ ]
                        }, {
                           "name" : "{urn:hl7-org:elm-types:r1}DateTime",
                           "type" : "NamedTypeSpecifier",
                           "annotation" : [ ]
                        } ],
                        "operand" : [ {
                           "locator" : "47:25-47:70",
                           "resultTypeName" : "{urn:hl7-org:elm-types:r1}DateTime",
                           "type" : "Start",
                           "annotation" : [ ],
                           "signature" : [ {
                              "type" : "IntervalTypeSpecifier",
                              "annotation" : [ ],
                              "pointType" : {
                                 "name" : "{urn:hl7-org:elm-types:r1}DateTime",
                                 "type" : "NamedTypeSpecifier",
                                 "annotation" : [ ]
                              }
                           } ],
                           "operand" : {
                              "locator" : "47:34-47:70",
                              "name" : "toInterval",
                              "libraryName" : "QICoreCommon",
                              "type" : "FunctionRef",
                              "annotation" : [ ],
                              "resultTypeSpecifier" : {
                                 "type" : "IntervalTypeSpecifier",
                                 "annotation" : [ ],
                                 "pointType" : {
                                    "name" : "{urn:hl7-org:elm-types:r1}DateTime",
                                    "type" : "NamedTypeSpecifier",
                                    "annotation" : [ ]
                                 }
                              },
                              "signature" : [ {
                                 "type" : "ChoiceTypeSpecifier",
                                 "annotation" : [ ],
                                 "choice" : [ {
                                    "name" : "{urn:hl7-org:elm-types:r1}DateTime",
                                    "type" : "NamedTypeSpecifier",
                                    "annotation" : [ ]
                                 }, {
                                    "name" : "{urn:hl7-org:elm-types:r1}Quantity",
                                    "type" : "NamedTypeSpecifier",
                                    "annotation" : [ ]
                                 }, {
                                    "type" : "IntervalTypeSpecifier",
                                    "annotation" : [ ],
                                    "pointType" : {
                                       "name" : "{urn:hl7-org:elm-types:r1}DateTime",
                                       "type" : "NamedTypeSpecifier",
                                       "annotation" : [ ]
                                    }
                                 }, {
                                    "type" : "IntervalTypeSpecifier",
                                    "annotation" : [ ],
                                    "pointType" : {
                                       "name" : "{urn:hl7-org:elm-types:r1}Quantity",
                                       "type" : "NamedTypeSpecifier",
                                       "annotation" : [ ]
                                    }
                                 }, {
                                    "name" : "{http://hl7.org/fhir}Timing",
                                    "type" : "NamedTypeSpecifier",
                                    "annotation" : [ ]
                                 } ]
                              } ],
                              "operand" : [ {
                                 "locator" : "47:34-47:57",
                                 "name" : "ToValue",
                                 "libraryName" : "FHIRHelpers",
                                 "type" : "FunctionRef",
                                 "annotation" : [ ],
                                 "resultTypeSpecifier" : {
                                    "type" : "ChoiceTypeSpecifier",
                                    "annotation" : [ ],
                                    "choice" : [ {
                                       "name" : "{urn:hl7-org:elm-types:r1}DateTime",
                                       "type" : "NamedTypeSpecifier",
                                       "annotation" : [ ]
                                    }, {
                                       "type" : "IntervalTypeSpecifier",
                                       "annotation" : [ ],
                                       "pointType" : {
                                          "name" : "{urn:hl7-org:elm-types:r1}DateTime",
                                          "type" : "NamedTypeSpecifier",
                                          "annotation" : [ ]
                                       }
                                    } ]
                                 },
                                 "signature" : [ ],
                                 "operand" : [ {
                                    "path" : "performed",
                                    "scope" : "ComfortMeasure",
                                    "type" : "Property",
                                    "annotation" : [ ]
                                 } ]
                              } ]
                           }
                        }, {
                           "locator" : "47:73-47:97",
                           "resultTypeName" : "{urn:hl7-org:elm-types:r1}DateTime",
                           "path" : "value",
                           "type" : "Property",
                           "annotation" : [ ],
                           "source" : {
                              "path" : "authoredOn",
                              "scope" : "ComfortMeasure",
                              "type" : "Property",
                              "annotation" : [ ]
                           }
                        } ]
                     }, {
                        "locator" : "47:107-47:162",
                        "name" : "hospitalizationWithObservation",
                        "libraryName" : "CQMCommon",
                        "type" : "FunctionRef",
                        "annotation" : [ ],
                        "resultTypeSpecifier" : {
                           "type" : "IntervalTypeSpecifier",
                           "annotation" : [ ],
                           "pointType" : {
                              "name" : "{urn:hl7-org:elm-types:r1}DateTime",
                              "type" : "NamedTypeSpecifier",
                              "annotation" : [ ]
                           }
                        },
                        "signature" : [ {
                           "name" : "{http://hl7.org/fhir}Encounter",
                           "type" : "NamedTypeSpecifier",
                           "annotation" : [ ]
                        } ],
                        "operand" : [ {
                           "locator" : "47:107-47:129",
                           "resultTypeName" : "{http://hl7.org/fhir}Encounter",
                           "name" : "IschemicStrokeEncounter",
                           "type" : "AliasRef",
                           "annotation" : [ ]
                        } ]
                     } ]
                  }
               } ]
            }
         }, {
            "locator" : "49:1-52:162",
            "name" : "Encounter With Comfort Measures During Hospitalization",
            "context" : "Patient",
            "accessLevel" : "Public",
            "annotation" : [ ],
            "resultTypeSpecifier" : {
               "type" : "ListTypeSpecifier",
               "annotation" : [ ],
               "elementType" : {
                  "name" : "{http://hl7.org/fhir}Encounter",
                  "type" : "NamedTypeSpecifier",
                  "annotation" : [ ]
               }
            },
            "expression" : {
               "locator" : "50:3-52:162",
               "type" : "Query",
               "annotation" : [ ],
               "resultTypeSpecifier" : {
                  "type" : "ListTypeSpecifier",
                  "annotation" : [ ],
                  "elementType" : {
                     "name" : "{http://hl7.org/fhir}Encounter",
                     "type" : "NamedTypeSpecifier",
                     "annotation" : [ ]
                  }
               },
               "source" : [ {
                  "locator" : "50:3-50:53",
                  "alias" : "IschemicStrokeEncounter",
                  "annotation" : [ ],
                  "resultTypeSpecifier" : {
                     "type" : "ListTypeSpecifier",
                     "annotation" : [ ],
                     "elementType" : {
                        "name" : "{http://hl7.org/fhir}Encounter",
                        "type" : "NamedTypeSpecifier",
                        "annotation" : [ ]
                     }
                  },
                  "expression" : {
                     "locator" : "50:3-50:29",
                     "name" : "Ischemic Stroke Encounter",
                     "type" : "ExpressionRef",
                     "annotation" : [ ],
                     "resultTypeSpecifier" : {
                        "type" : "ListTypeSpecifier",
                        "annotation" : [ ],
                        "elementType" : {
                           "name" : "{http://hl7.org/fhir}Encounter",
                           "type" : "NamedTypeSpecifier",
                           "annotation" : [ ]
                        }
                     }
                  }
               } ],
               "let" : [ ],
               "relationship" : [ {
                  "locator" : "51:5-52:162",
                  "alias" : "ComfortMeasure",
                  "type" : "With",
                  "annotation" : [ ],
                  "resultTypeSpecifier" : {
                     "type" : "ListTypeSpecifier",
                     "annotation" : [ ],
                     "elementType" : {
                        "type" : "ChoiceTypeSpecifier",
                        "annotation" : [ ],
                        "choice" : [ {
                           "name" : "{http://hl7.org/fhir}ServiceRequest",
                           "type" : "NamedTypeSpecifier",
                           "annotation" : [ ]
                        }, {
                           "name" : "{http://hl7.org/fhir}Procedure",
                           "type" : "NamedTypeSpecifier",
                           "annotation" : [ ]
                        } ]
                     }
                  },
                  "expression" : {
                     "locator" : "51:10-51:40",
                     "name" : "Intervention Comfort Measures",
                     "type" : "ExpressionRef",
                     "annotation" : [ ],
                     "resultTypeSpecifier" : {
                        "type" : "ListTypeSpecifier",
                        "annotation" : [ ],
                        "elementType" : {
                           "type" : "ChoiceTypeSpecifier",
                           "annotation" : [ ],
                           "choice" : [ {
                              "name" : "{http://hl7.org/fhir}ServiceRequest",
                              "type" : "NamedTypeSpecifier",
                              "annotation" : [ ]
                           }, {
                              "name" : "{http://hl7.org/fhir}Procedure",
                              "type" : "NamedTypeSpecifier",
                              "annotation" : [ ]
                           } ]
                        }
                     }
                  },
                  "suchThat" : {
                     "locator" : "52:16-52:162",
                     "resultTypeName" : "{urn:hl7-org:elm-types:r1}Boolean",
                     "type" : "In",
                     "annotation" : [ ],
                     "signature" : [ {
                        "name" : "{urn:hl7-org:elm-types:r1}DateTime",
                        "type" : "NamedTypeSpecifier",
                        "annotation" : [ ]
                     }, {
                        "type" : "IntervalTypeSpecifier",
                        "annotation" : [ ],
                        "pointType" : {
                           "name" : "{urn:hl7-org:elm-types:r1}DateTime",
                           "type" : "NamedTypeSpecifier",
                           "annotation" : [ ]
                        }
                     } ],
                     "operand" : [ {
                        "locator" : "52:16-52:98",
                        "resultTypeName" : "{urn:hl7-org:elm-types:r1}DateTime",
                        "type" : "Coalesce",
                        "annotation" : [ ],
                        "signature" : [ {
                           "name" : "{urn:hl7-org:elm-types:r1}DateTime",
                           "type" : "NamedTypeSpecifier",
                           "annotation" : [ ]
                        }, {
                           "name" : "{urn:hl7-org:elm-types:r1}DateTime",
                           "type" : "NamedTypeSpecifier",
                           "annotation" : [ ]
                        } ],
                        "operand" : [ {
                           "locator" : "52:25-52:70",
                           "resultTypeName" : "{urn:hl7-org:elm-types:r1}DateTime",
                           "type" : "Start",
                           "annotation" : [ ],
                           "signature" : [ {
                              "type" : "IntervalTypeSpecifier",
                              "annotation" : [ ],
                              "pointType" : {
                                 "name" : "{urn:hl7-org:elm-types:r1}DateTime",
                                 "type" : "NamedTypeSpecifier",
                                 "annotation" : [ ]
                              }
                           } ],
                           "operand" : {
                              "locator" : "52:34-52:70",
                              "name" : "toInterval",
                              "libraryName" : "QICoreCommon",
                              "type" : "FunctionRef",
                              "annotation" : [ ],
                              "resultTypeSpecifier" : {
                                 "type" : "IntervalTypeSpecifier",
                                 "annotation" : [ ],
                                 "pointType" : {
                                    "name" : "{urn:hl7-org:elm-types:r1}DateTime",
                                    "type" : "NamedTypeSpecifier",
                                    "annotation" : [ ]
                                 }
                              },
                              "signature" : [ {
                                 "type" : "ChoiceTypeSpecifier",
                                 "annotation" : [ ],
                                 "choice" : [ {
                                    "name" : "{urn:hl7-org:elm-types:r1}DateTime",
                                    "type" : "NamedTypeSpecifier",
                                    "annotation" : [ ]
                                 }, {
                                    "name" : "{urn:hl7-org:elm-types:r1}Quantity",
                                    "type" : "NamedTypeSpecifier",
                                    "annotation" : [ ]
                                 }, {
                                    "type" : "IntervalTypeSpecifier",
                                    "annotation" : [ ],
                                    "pointType" : {
                                       "name" : "{urn:hl7-org:elm-types:r1}DateTime",
                                       "type" : "NamedTypeSpecifier",
                                       "annotation" : [ ]
                                    }
                                 }, {
                                    "type" : "IntervalTypeSpecifier",
                                    "annotation" : [ ],
                                    "pointType" : {
                                       "name" : "{urn:hl7-org:elm-types:r1}Quantity",
                                       "type" : "NamedTypeSpecifier",
                                       "annotation" : [ ]
                                    }
                                 }, {
                                    "name" : "{http://hl7.org/fhir}Timing",
                                    "type" : "NamedTypeSpecifier",
                                    "annotation" : [ ]
                                 } ]
                              } ],
                              "operand" : [ {
                                 "locator" : "52:34-52:57",
                                 "name" : "ToValue",
                                 "libraryName" : "FHIRHelpers",
                                 "type" : "FunctionRef",
                                 "annotation" : [ ],
                                 "resultTypeSpecifier" : {
                                    "type" : "ChoiceTypeSpecifier",
                                    "annotation" : [ ],
                                    "choice" : [ {
                                       "name" : "{urn:hl7-org:elm-types:r1}DateTime",
                                       "type" : "NamedTypeSpecifier",
                                       "annotation" : [ ]
                                    }, {
                                       "type" : "IntervalTypeSpecifier",
                                       "annotation" : [ ],
                                       "pointType" : {
                                          "name" : "{urn:hl7-org:elm-types:r1}DateTime",
                                          "type" : "NamedTypeSpecifier",
                                          "annotation" : [ ]
                                       }
                                    } ]
                                 },
                                 "signature" : [ ],
                                 "operand" : [ {
                                    "path" : "performed",
                                    "scope" : "ComfortMeasure",
                                    "type" : "Property",
                                    "annotation" : [ ]
                                 } ]
                              } ]
                           }
                        }, {
                           "locator" : "52:73-52:97",
                           "resultTypeName" : "{urn:hl7-org:elm-types:r1}DateTime",
                           "path" : "value",
                           "type" : "Property",
                           "annotation" : [ ],
                           "source" : {
                              "path" : "authoredOn",
                              "scope" : "ComfortMeasure",
                              "type" : "Property",
                              "annotation" : [ ]
                           }
                        } ]
                     }, {
                        "locator" : "52:107-52:162",
                        "name" : "hospitalizationWithObservation",
                        "libraryName" : "CQMCommon",
                        "type" : "FunctionRef",
                        "annotation" : [ ],
                        "resultTypeSpecifier" : {
                           "type" : "IntervalTypeSpecifier",
                           "annotation" : [ ],
                           "pointType" : {
                              "name" : "{urn:hl7-org:elm-types:r1}DateTime",
                              "type" : "NamedTypeSpecifier",
                              "annotation" : [ ]
                           }
                        },
                        "signature" : [ {
                           "name" : "{http://hl7.org/fhir}Encounter",
                           "type" : "NamedTypeSpecifier",
                           "annotation" : [ ]
                        } ],
                        "operand" : [ {
                           "locator" : "52:107-52:129",
                           "resultTypeName" : "{http://hl7.org/fhir}Encounter",
                           "name" : "IschemicStrokeEncounter",
                           "type" : "AliasRef",
                           "annotation" : [ ]
                        } ]
                     } ]
                  }
               } ]
            }
         }, {
            "locator" : "64:1-65:67",
            "name" : "CalendarDayOfOrDayAfter",
            "context" : "Patient",
            "accessLevel" : "Public",
            "fluent" : true,
            "type" : "FunctionDef",
            "annotation" : [ ],
            "resultTypeSpecifier" : {
               "type" : "IntervalTypeSpecifier",
               "annotation" : [ ],
               "pointType" : {
                  "name" : "{urn:hl7-org:elm-types:r1}Date",
                  "type" : "NamedTypeSpecifier",
                  "annotation" : [ ]
               }
            },
            "expression" : {
               "locator" : "65:3-65:67",
               "lowClosed" : true,
               "highClosed" : true,
               "type" : "Interval",
               "annotation" : [ ],
               "resultTypeSpecifier" : {
                  "type" : "IntervalTypeSpecifier",
                  "annotation" : [ ],
                  "pointType" : {
                     "name" : "{urn:hl7-org:elm-types:r1}Date",
                     "type" : "NamedTypeSpecifier",
                     "annotation" : [ ]
                  }
               },
               "low" : {
                  "locator" : "65:13-65:34",
                  "resultTypeName" : "{urn:hl7-org:elm-types:r1}Date",
                  "type" : "DateFrom",
                  "annotation" : [ ],
                  "signature" : [ {
                     "name" : "{urn:hl7-org:elm-types:r1}DateTime",
                     "type" : "NamedTypeSpecifier",
                     "annotation" : [ ]
                  } ],
                  "operand" : {
                     "locator" : "65:23-65:34",
                     "resultTypeName" : "{urn:hl7-org:elm-types:r1}DateTime",
                     "name" : "StartValue",
                     "type" : "OperandRef",
                     "annotation" : [ ]
                  }
               },
               "high" : {
                  "locator" : "65:37-65:66",
                  "resultTypeName" : "{urn:hl7-org:elm-types:r1}Date",
                  "type" : "Add",
                  "annotation" : [ ],
                  "signature" : [ {
                     "name" : "{urn:hl7-org:elm-types:r1}Date",
                     "type" : "NamedTypeSpecifier",
                     "annotation" : [ ]
                  }, {
                     "name" : "{urn:hl7-org:elm-types:r1}Quantity",
                     "type" : "NamedTypeSpecifier",
                     "annotation" : [ ]
                  } ],
                  "operand" : [ {
                     "locator" : "65:37-65:58",
                     "resultTypeName" : "{urn:hl7-org:elm-types:r1}Date",
                     "type" : "DateFrom",
                     "annotation" : [ ],
                     "signature" : [ {
                        "name" : "{urn:hl7-org:elm-types:r1}DateTime",
                        "type" : "NamedTypeSpecifier",
                        "annotation" : [ ]
                     } ],
                     "operand" : {
                        "locator" : "65:47-65:58",
                        "resultTypeName" : "{urn:hl7-org:elm-types:r1}DateTime",
                        "name" : "StartValue",
                        "type" : "OperandRef",
                        "annotation" : [ ]
                     }
                  }, {
                     "locator" : "65:62-65:66",
                     "resultTypeName" : "{urn:hl7-org:elm-types:r1}Quantity",
                     "value" : 1,
                     "unit" : "day",
                     "type" : "Quantity",
                     "annotation" : [ ]
                  } ]
               }
            },
            "operand" : [ {
               "name" : "StartValue",
               "annotation" : [ ],
               "operandTypeSpecifier" : {
                  "locator" : "64:59-64:66",
                  "resultTypeName" : "{urn:hl7-org:elm-types:r1}DateTime",
                  "name" : "{urn:hl7-org:elm-types:r1}DateTime",
                  "type" : "NamedTypeSpecifier",
                  "annotation" : [ ]
               }
            } ]
         } ]
      }
   }
}

